{
	"nodes": {
		"lfo_1": {
			"_props": {
				"kind": "lfo",
				"pos": [
					-0.9017414411180378,
					1.4013176806168608,
					-0.4336915612082502
				],
				"orient": [
					0.3742201037719189,
					0.301970851842824,
					0.0942331223232973,
					0.8717184391920684
				]
			},
			"fm_cv": {
				"_props": {
					"kind": "inlet",
					"index": 0
				}
			},
			"phasor_sync": {
				"_props": {
					"kind": "inlet",
					"index": 1
				}
			},
			"pulse_width_cv": {
				"_props": {
					"kind": "inlet",
					"index": 2
				}
			},
			"rate": {
				"_props": {
					"kind": "large_knob",
					"range": [
						0,
						80
					],
					"taper": "log 3.8",
					"value": 0.17,
					"unit": "Hz"
				}
			},
			"index": {
				"_props": {
					"kind": "small_knob",
					"range": [
						0,
						10
					],
					"taper": "linear",
					"value": 3,
					"unit": "float"
				}
			},
			"pulse_width": {
				"_props": {
					"kind": "small_knob",
					"range": [
						0,
						1
					],
					"taper": "linear",
					"value": 5,
					"unit": "float"
				}
			},
			"onset": {
				"_props": {
					"kind": "small_knob",
					"range": [
						0,
						1
					],
					"taper": "linear",
					"value": 2.8,
					"unit": "float"
				}
			},
			"sine": {
				"_props": {
					"kind": "outlet",
					"index": 0
				}
			},
			"phasor": {
				"_props": {
					"kind": "outlet",
					"index": 1
				}
			},
			"pulse": {
				"_props": {
					"kind": "outlet",
					"index": 2
				}
			},
			"sine_index": {
				"_props": {
					"kind": "outlet",
					"index": 3
				}
			}
		},
		"lfo_2": {
			"_props": {
				"kind": "lfo",
				"pos": [
					-0.746813966552653,
					1.1208045593304417,
					-0.7201232433217533
				],
				"orient": [
					0.10565612843707434,
					0.2872192823467816,
					0.1077334123441249,
					0.9459045291341929
				]
			},
			"fm_cv": {
				"_props": {
					"kind": "inlet",
					"index": 0
				}
			},
			"phasor_sync": {
				"_props": {
					"kind": "inlet",
					"index": 1
				}
			},
			"pulse_width_cv": {
				"_props": {
					"kind": "inlet",
					"index": 2
				}
			},
			"rate": {
				"_props": {
					"kind": "large_knob",
					"range": [
						0,
						80
					],
					"taper": "log 3.8",
					"value": 375,
					"unit": "Hz"
				}
			},
			"index": {
				"_props": {
					"kind": "small_knob",
					"range": [
						0,
						10
					],
					"taper": "linear",
					"value": 21.9,
					"unit": "float"
				}
			},
			"pulse_width": {
				"_props": {
					"kind": "small_knob",
					"range": [
						0,
						1
					],
					"taper": "linear",
					"value": 0.6,
					"unit": "float"
				}
			},
			"onset": {
				"_props": {
					"kind": "small_knob",
					"range": [
						0,
						1
					],
					"taper": "linear",
					"value": 0.74,
					"unit": "float"
				}
			},
			"sine": {
				"_props": {
					"kind": "outlet",
					"index": 0
				}
			},
			"phasor": {
				"_props": {
					"kind": "outlet",
					"index": 1
				}
			},
			"pulse": {
				"_props": {
					"kind": "outlet",
					"index": 2
				}
			},
			"sine_index": {
				"_props": {
					"kind": "outlet",
					"index": 3
				}
			}
		},
		"dualvco_1": {
			"_props": {
				"kind": "dualvco",
				"pos": [
					-0.28377446888110897,
					1.14023206676233,
					-0.7858741355851256
				],
				"orient": [
					0.40585274337842275,
					0.24208779254960244,
					0.14515818791056145,
					0.8692560910835341
				]
			},
			"vco_1_cv": {
				"_props": {
					"kind": "inlet",
					"index": 0
				}
			},
			"index_cv": {
				"_props": {
					"kind": "inlet",
					"index": 1
				}
			},
			"vco_2_cv": {
				"_props": {
					"kind": "inlet",
					"index": 1
				}
			},
			"feedback_cv": {
				"_props": {
					"kind": "inlet",
					"index": 2
				}
			},
			"vco_1_rate": {
				"_props": {
					"kind": "large_knob",
					"range": [
						0,
						6000
					],
					"taper": "log 3.8",
					"value": 61,
					"unit": "Hz"
				}
			},
			"vco_1_waveform": {
				"_props": {
					"kind": "n_switch",
					"throws": [
						"Sine",
						"Phasor",
						"Triangle"
					],
					"value": 2
				}
			},
			"vco_2_rate": {
				"_props": {
					"kind": "large_knob",
					"range": [
						0,
						6000
					],
					"taper": "log 3.8",
					"value": 17.6,
					"unit": "Hz"
				}
			},
			"vco_2_waveform": {
				"_props": {
					"kind": "n_switch",
					"throws": [
						"Sine",
						"Phasor",
						"Triangle"
					],
					"value": 1
				}
			},
			"feedback": {
				"_props": {
					"kind": "small_knob",
					"range": [
						0,
						6
					],
					"taper": "linear",
					"value": 6.7,
					"unit": "float"
				}
			},
			"vco_1": {
				"_props": {
					"kind": "outlet",
					"index": 0
				}
			},
			"vco_2": {
				"_props": {
					"kind": "outlet",
					"index": 1
				}
			},
			"master": {
				"_props": {
					"kind": "outlet",
					"index": 2
				}
			}
		},
		"vca_1": {
			"_props": {
				"kind": "vca",
				"pos": [
					0.19861967786729504,
					1.6951430131867675,
					-0.7681031677833332
				],
				"orient": [
					0.4734738148186381,
					-0.18725652484934643,
					-0.06437805100196019,
					0.8582616192814526
				]
			},
			"signal": {
				"_props": {
					"kind": "inlet",
					"index": 0
				}
			},
			"cv": {
				"_props": {
					"kind": "inlet",
					"index": 1
				}
			},
			"cv_amount": {
				"_props": {
					"kind": "large_knob",
					"range": [
						0,
						1
					],
					"taper": "linear",
					"value": 0.762,
					"unit": "float"
				}
			},
			"bias": {
				"_props": {
					"kind": "large_knob",
					"range": [
						0,
						1
					],
					"taper": "linear",
					"value": 0,
					"unit": "float"
				}
			},
			"output": {
				"_props": {
					"kind": "outlet",
					"index": 0
				}
			}
		},
		"comparator_1": {
			"_props": {
				"kind": "comparator",
				"pos": [
					-0.1683175584207885,
					1.472470843193285,
					-0.8406020768211364
				],
				"orient": [
					0.2062087534879719,
					0.05838717625119117,
					0.0852153150938516,
					0.9730402035413567
				]
			},
			"A": {
				"_props": {
					"kind": "inlet",
					"index": 0
				}
			},
			"B": {
				"_props": {
					"kind": "inlet",
					"index": 1
				}
			},
			"max": {
				"_props": {
					"kind": "outlet",
					"index": 0
				}
			},
			"min": {
				"_props": {
					"kind": "outlet",
					"index": 1
				}
			}
		},
		"outs_1": {
			"_props": {
				"kind": "outs",
				"pos": [
					0.26281435575774936,
					1.247030070534667,
					-1.1116201183897458
				],
				"orient": [
					-0.09429164552164376,
					-0.1954886111546801,
					-0.4011787082444528,
					0.8899151265725104
				]
			},
			"left_(mono)": {
				"_props": {
					"kind": "inlet",
					"index": 0
				}
			},
			"right_(stereo)": {
				"_props": {
					"kind": "inlet",
					"index": 1
				}
			},
			"volume": {
				"_props": {
					"kind": "small_knob",
					"range": [
						0,
						1
					],
					"taper": "log 3.8",
					"value": 1,
					"unit": "float"
				}
			},
			"left": {
				"_props": {
					"kind": "outlet",
					"index": 0
				}
			},
			"right": {
				"_props": {
					"kind": "outlet",
					"index": 0
				}
			}
		}
	},
	"arcs": [
		[
			"lfo_1.sine",
			"vca_1.signal"
		],
		[
			"lfo_1.sine",
			"lfo_2.fm_cv"
		],
		[
			"lfo_2.sine",
			"vca_1.cv"
		],
		[
			"lfo_1.phasor",
			"dualvco_1.feedback_cv"
		],
		[
			"lfo_1.pulse",
			"dualvco_1.vco_1_cv"
		],
		[
			"dualvco_1.master",
			"comparator_1.B"
		],
		[
			"comparator_1.max",
			"outs_1.left_(mono)"
		],
		[
			"comparator_1.min",
			"outs_1.right_(stereo)"
		],
		[
			"dualvco_1.master",
			"dualvco_1.vco_2_cv"
		],
		[
			"vca_1.output",
			"comparator_1.A"
		]
	]
}